py_adobeio_api/__init__.py
py_adobeio_api/libs/__init__.py
py_adobeio_api/libs/adobe_rest.py
py_adobeio_api/libs/basiclog.py
py_adobeio_api/libs/common_auth.py
py_adobeio_api-0.41.dist-info/LICENSE
py_adobeio_api-0.41.dist-info/METADATA
py_adobeio_api-0.41.dist-info/WHEEL
py_adobeio_api-0.41.dist-info/top_level.txt
py_adobeio_api-0.41.dist-info/RECORD
